<?xml version="1.0" encoding="UTF-8"?><record_update>
    <sys_choice action="INSERT_OR_UPDATE" field="state" table="x_788509_track_ret_tracking_task" version="3">
        <sys_choice_set action="INSERT_OR_UPDATE">
            <element>state</element>
            <name>x_788509_track_ret_tracking_task</name>
            <sys_class_name>sys_choice_set</sys_class_name>
            <sys_created_by>admin</sys_created_by>
            <sys_created_on>2022-06-01 03:51:20</sys_created_on>
            <sys_id>8401eab52f7f011046e755f62799b674</sys_id>
            <sys_mod_count>0</sys_mod_count>
            <sys_name>state</sys_name>
            <sys_package display_value="Track Return" source="x_788509_track_ret">0b435ab92f3f011046e755f62799b694</sys_package>
            <sys_policy/>
            <sys_scope display_value="Track Return">0b435ab92f3f011046e755f62799b694</sys_scope>
            <sys_update_name>sys_choice_x_788509_track_ret_tracking_task_state</sys_update_name>
            <sys_updated_by>admin</sys_updated_by>
            <sys_updated_on>2022-06-01 03:51:20</sys_updated_on>
        </sys_choice_set>
        <sys_choice action="INSERT_OR_UPDATE">
            <dependent_value/>
            <element>state</element>
            <hint/>
            <inactive>false</inactive>
            <label>Open</label>
            <language>en</language>
            <name>x_788509_track_ret_tracking_task</name>
            <sequence>0</sequence>
            <synonyms/>
            <sys_created_by>admin</sys_created_by>
            <sys_created_on>2022-06-01 03:51:20</sys_created_on>
            <sys_domain>global</sys_domain>
            <sys_domain_path>/</sys_domain_path>
            <sys_id>4c01eab52f7f011046e755f62799b673</sys_id>
            <sys_mod_count>0</sys_mod_count>
            <sys_updated_by>admin</sys_updated_by>
            <sys_updated_on>2022-06-01 03:51:20</sys_updated_on>
            <value>1</value>
        </sys_choice>
        <sys_choice action="INSERT_OR_UPDATE">
            <dependent_value/>
            <element>state</element>
            <hint/>
            <inactive>false</inactive>
            <label>Closed Complete</label>
            <language>en</language>
            <name>x_788509_track_ret_tracking_task</name>
            <sequence>1</sequence>
            <synonyms/>
            <sys_created_by>admin</sys_created_by>
            <sys_created_on>2022-06-01 03:51:20</sys_created_on>
            <sys_domain>global</sys_domain>
            <sys_domain_path>/</sys_domain_path>
            <sys_id>8401eab52f7f011046e755f62799b676</sys_id>
            <sys_mod_count>0</sys_mod_count>
            <sys_updated_by>admin</sys_updated_by>
            <sys_updated_on>2022-06-01 03:51:20</sys_updated_on>
            <value>3</value>
        </sys_choice>
        <sys_choice action="INSERT_OR_UPDATE">
            <dependent_value/>
            <element>state</element>
            <hint/>
            <inactive>false</inactive>
            <label>Rejected</label>
            <language>en</language>
            <name>x_788509_track_ret_tracking_task</name>
            <sequence>2</sequence>
            <synonyms/>
            <sys_created_by>admin</sys_created_by>
            <sys_created_on>2022-06-01 03:51:20</sys_created_on>
            <sys_domain>global</sys_domain>
            <sys_domain_path>/</sys_domain_path>
            <sys_id>d001eab52f7f011046e755f62799b685</sys_id>
            <sys_mod_count>0</sys_mod_count>
            <sys_updated_by>admin</sys_updated_by>
            <sys_updated_on>2022-06-01 03:51:20</sys_updated_on>
            <value>10</value>
        </sys_choice>
    </sys_choice>
</record_update>
